promptkit/__init__.py
promptkit/__main__.py
promptkit/cli/main.py
promptkit/core/compiler.py
promptkit/core/loader.py
promptkit/core/prompt.py
promptkit/core/runner.py
promptkit/core/schema.py
promptkit/engines/__init__.py
promptkit/engines/base.py
promptkit/engines/ollama.py
promptkit/engines/openai.py
promptkit/tests/__init__.py
promptkit/tests/test_prompt.py
promptkit/utils/logging.py
promptkit/utils/tokens.py
promptkit_core-0.1.0.dist-info/METADATA
promptkit_core-0.1.0.dist-info/WHEEL
promptkit_core-0.1.0.dist-info/entry_points.txt
promptkit_core-0.1.0.dist-info/licenses/LICENSE
promptkit_core-0.1.0.dist-info/RECORD
