Metadata-Version: 2.4
Name: promptkit-core
Version: 0.1.0
Summary: Structured Prompt Engineering for LLM Apps
Project-URL: Homepage, https://github.com/ochotzas/promptkit
Project-URL: Repository, https://github.com/ochotzas/promptkit
Project-URL: Issues, https://github.com/ochotzas/promptkit/issues
Author-email: Olger Chotza <olgerdev@icloud.com>
License: MIT
License-File: LICENSE
Requires-Python: >=3.10
Requires-Dist: httpx>=0.25
Requires-Dist: jinja2>=3.1
Requires-Dist: pydantic>=2.5
Requires-Dist: pyyaml>=6.0
Requires-Dist: rich>=13.0
Requires-Dist: typer[all]>=0.9
Provides-Extra: dev
Requires-Dist: black>=23.0; extra == 'dev'
Requires-Dist: isort>=5.12; extra == 'dev'
Requires-Dist: mypy>=1.5; extra == 'dev'
Requires-Dist: pre-commit>=3.0; extra == 'dev'
Requires-Dist: pytest-asyncio>=0.21; extra == 'dev'
Requires-Dist: pytest-cov>=4.0; extra == 'dev'
Requires-Dist: pytest>=7.0; extra == 'dev'
Requires-Dist: ruff>=0.1.0; extra == 'dev'
Requires-Dist: types-pyyaml; extra == 'dev'
Provides-Extra: docs
Requires-Dist: linkify-it-py>=2.0.0; extra == 'docs'
Requires-Dist: myst-parser>=2.0.0; extra == 'docs'
Requires-Dist: sphinx-autobuild>=2021.3.14; extra == 'docs'
Requires-Dist: sphinx-rtd-theme>=2.0.0; extra == 'docs'
Requires-Dist: sphinx>=7.0.0; extra == 'docs'
